[
  {
    "gid": "1207345918598209",
    "completed": true,
    "completed_at": "2024-05-17T14:04:28.915Z",
    "created_at": "2024-05-17T13:59:59.068Z",
    "name": "Onboarding Meeting"
  },
  {
    "gid": "1207345918598217",
    "completed": true,
    "completed_at": "2025-02-24T20:51:35.473Z",
    "created_at": "2024-05-17T13:59:59.762Z",
    "name": "Assets"
  },
  {
    "gid": "1207345918598225",
    "completed": true,
    "completed_at": "2024-05-22T18:50:03.057Z",
    "created_at": "2024-05-17T14:00:00.392Z",
    "name": "Creative Brief"
  },
  {
    "gid": "1207345918598234",
    "completed": true,
    "completed_at": "2024-06-18T19:15:34.503Z",
    "created_at": "2024-05-17T14:00:01.238Z",
    "name": "Written Content"
  },
  {
    "gid": "1207345918751439",
    "completed": true,
    "completed_at": "2024-08-09T20:29:10.668Z",
    "created_at": "2024-05-17T14:00:04.961Z",
    "name": "Design Mockup"
  },
  {
    "gid": "1207345918751446",
    "completed": true,
    "completed_at": "2024-09-26T19:08:38.445Z",
    "created_at": "2024-05-17T14:00:05.518Z",
    "name": "Mobile Mockup"
  },
  {
    "gid": "1207345919059713",
    "completed": true,
    "completed_at": "2024-08-29T13:44:31.215Z",
    "created_at": "2024-05-17T14:00:06.070Z",
    "name": "Mockup Internal Review"
  },
  {
    "gid": "1207345919059720",
    "completed": true,
    "completed_at": "2024-09-03T19:48:23.764Z",
    "created_at": "2024-05-17T14:00:07.160Z",
    "name": "Mockup Client Revisions"
  },
  {
    "gid": "1207345919059727",
    "completed": true,
    "completed_at": "2024-09-25T20:21:37.931Z",
    "created_at": "2024-05-17T14:00:07.646Z",
    "name": "Gather Photos and Assets into Google Folder"
  },
  {
    "gid": "1209125684884647",
    "completed": true,
    "completed_at": "2025-02-25T15:56:49.220Z",
    "created_at": "2025-01-10T20:23:55.212Z",
    "name": "QuickPay Link"
  },
  {
    "gid": "1208955350849977",
    "completed": true,
    "completed_at": "2025-01-10T21:44:22.879Z",
    "created_at": "2024-12-12T14:20:09.081Z",
    "name": "ADDs Connection"
  },
  {
    "gid": "1208101820918713",
    "completed": true,
    "completed_at": "2024-09-16T18:44:40.587Z",
    "created_at": "2024-08-20T14:24:10.194Z",
    "name": "ADDs Integration Instructions"
  },
  {
    "gid": "1207345919129082",
    "completed": true,
    "completed_at": "2024-10-17T19:32:03.045Z",
    "created_at": "2024-05-17T14:00:14.632Z",
    "name": "Development"
  },
  {
    "gid": "1207345919577377",
    "completed": true,
    "completed_at": "2024-11-12T15:32:35.649Z",
    "created_at": "2024-05-17T14:00:15.271Z",
    "name": "Development Internal Review"
  },
  {
    "gid": "1207345919577384",
    "completed": true,
    "completed_at": "2024-12-12T14:19:50.956Z",
    "created_at": "2024-05-17T14:00:15.829Z",
    "name": "Development Client Revisions"
  },
  {
    "gid": "1207345917920194",
    "completed": true,
    "completed_at": "2024-12-11T18:48:38.177Z",
    "created_at": "2024-05-17T14:00:19.206Z",
    "name": "Launch"
  },
  {
    "gid": "1207345917920201",
    "completed": true,
    "completed_at": "2024-12-20T19:21:25.313Z",
    "created_at": "2024-05-17T14:00:19.771Z",
    "name": "Training Videos"
  }
]