[
  {
    "gid": "1211470890494454",
    "completed": true,
    "completed_at": "2025-10-01T20:11:34.775Z",
    "created_at": "2025-09-25T18:43:23.888Z",
    "name": "Onboarding meeting"
  },
  {
    "gid": "1211470890494457",
    "completed": true,
    "completed_at": "2025-10-01T20:11:38.499Z",
    "created_at": "2025-09-25T18:43:35.133Z",
    "name": "Gather assets"
  },
  {
    "gid": "1211471619347860",
    "completed": false,
    "completed_at": null,
    "created_at": "2025-09-25T20:13:00.928Z",
    "name": "Round 1"
  },
  {
    "gid": "1211471619347862",
    "completed": false,
    "completed_at": null,
    "created_at": "2025-09-26T13:02:16.844Z",
    "name": "Review"
  },
  {
    "gid": "1211470890494466",
    "completed": false,
    "completed_at": null,
    "created_at": "2025-09-25T18:44:32.974Z",
    "name": "Deliver First Concept"
  },
  {
    "gid": "1211470890494470",
    "completed": false,
    "completed_at": null,
    "created_at": "2025-09-25T18:44:48.978Z",
    "name": "Client Feedback"
  },
  {
    "gid": "1211471619027182",
    "completed": false,
    "completed_at": null,
    "created_at": "2025-09-25T20:12:48.476Z",
    "name": "Round 2"
  },
  {
    "gid": "1211471619347864",
    "completed": false,
    "completed_at": null,
    "created_at": "2025-09-26T13:04:56.311Z",
    "name": "Review"
  },
  {
    "gid": "1211470890494477",
    "completed": false,
    "completed_at": null,
    "created_at": "2025-09-25T18:45:19.642Z",
    "name": "Deliver Second Concept"
  },
  {
    "gid": "1211470891163606",
    "completed": false,
    "completed_at": null,
    "created_at": "2025-09-25T18:45:29.200Z",
    "name": "Client Feedback"
  },
  {
    "gid": "1211471619027170",
    "completed": false,
    "completed_at": null,
    "created_at": "2025-09-25T20:02:45.810Z",
    "name": "Round 3"
  },
  {
    "gid": "1211470891163613",
    "completed": false,
    "completed_at": null,
    "created_at": "2025-09-25T18:46:07.479Z",
    "name": "Deliver to Client"
  },
  {
    "gid": "1211471619027165",
    "completed": false,
    "completed_at": null,
    "created_at": "2025-09-25T19:59:48.788Z",
    "name": "Final Logo Approval"
  },
  {
    "gid": "1211470891163616",
    "completed": false,
    "completed_at": null,
    "created_at": "2025-09-25T18:46:19.307Z",
    "name": "Deliverables"
  },
  {
    "gid": "1211470891163622",
    "completed": false,
    "completed_at": null,
    "created_at": "2025-09-25T18:46:41.988Z",
    "name": "Send to Client"
  }
]